README.md
setup.py
trading_gym/__init__.py
trading_gym/env.py
trading_gym/exchange.py
trading_gym/inputs.py
trading_gym/render.py
trading_gym/ta.py
trading_gym.egg-info/PKG-INFO
trading_gym.egg-info/SOURCES.txt
trading_gym.egg-info/dependency_links.txt
trading_gym.egg-info/not-zip-safe
trading_gym.egg-info/requires.txt
trading_gym.egg-info/top_level.txt