Metadata-Version: 1.0
Name: trading-gym
Version: 0.1.5
Summary: A gym tool for trading.
Home-page: https://github.com/mymusise/Trading-Gym
Author: mymusise
Author-email: mymusise1@gmail.com
License: MIT
Platform: UNKNOWN
